ml_project_structure_creator/__init__.py
ml_project_structure_creator/create_ml_structure.py
ml_project_structure_creator-0.3.3.dist-info/LICENSE
ml_project_structure_creator-0.3.3.dist-info/METADATA
ml_project_structure_creator-0.3.3.dist-info/WHEEL
ml_project_structure_creator-0.3.3.dist-info/entry_points.txt
ml_project_structure_creator-0.3.3.dist-info/top_level.txt
ml_project_structure_creator-0.3.3.dist-info/RECORD
